arabia/__init__.py
arabia/core.py
arabia-1.0.0.dist-info/licenses/LICENSE
arabia-1.0.0.dist-info/METADATA
arabia-1.0.0.dist-info/WHEEL
arabia-1.0.0.dist-info/top_level.txt
arabia-1.0.0.dist-info/RECORD
