Metadata-Version: 2.4
Name: arabia
Version: 1.0.0
Summary: مكتبة عربية لتعليم Python للمبتدئين
Home-page: https://github.com/FoxCode-Moja/Arabia
Author: Moja
Classifier: Programming Language :: Python :: 3
Classifier: License :: OSI Approved :: MIT License
Classifier: Operating System :: OS Independent
Requires-Python: >=3.6
License-File: LICENSE
Dynamic: author
Dynamic: classifier
Dynamic: description
Dynamic: description-content-type
Dynamic: home-page
Dynamic: license-file
Dynamic: requires-python
Dynamic: summary
